logflex/__init__.py
logflex/logflex.py
logflex/config/settings.py
logflex/config/watcher.py
logflex/models/config_model.py
logflex/tests/__init__.py
logflex/tests/test_logflex.py
logflex-0.1.7.dist-info/METADATA
logflex-0.1.7.dist-info/WHEEL
logflex-0.1.7.dist-info/licenses/LICENSE.txt
logflex-0.1.7.dist-info/RECORD
