Metadata-Version: 2.4
Name: logflex
Version: 0.1.7
Summary: LogFlex, a robust and flexible logging extension for Python, enhances the standard logging module by providing streamlined configuration via environmental variables and TOML files. This library supports comprehensive log management with features like dynamic log levels, multiple output handlers (console, file, and Syslog), and automatic log rotation. Ideal for developers looking to implement advanced logging practices easily in any Python application.
Author-email: kon0n0 <kono@ms1.kononet.jp>
License-Expression: MIT
License-File: LICENSE.txt
Requires-Python: >=3.10
Requires-Dist: colorlog>=6.8.2
Requires-Dist: dacite>=1.8.1
Requires-Dist: toml>=0.10.2
Requires-Dist: watchdog>=6.0.0
